{
    "VERSION": "1.2",
    "format": "TTT",
    "statistics": {
        "max": 1380,
        "frequencyTable": [
            {
                "key": 180,
                "value": 1
            },
            {
                "key": 210,
                "value": 1
            },
            {
                "key": 220,
                "value": 4
            },
            {
                "key": 230,
                "value": 3
            },
            {
                "key": 240,
                "value": 11
            },
            {
                "key": 250,
                "value": 13
            },
            {
                "key": 260,
                "value": 28
            },
            {
                "key": 270,
                "value": 49
            },
            {
                "key": 280,
                "value": 59
            },
            {
                "key": 290,
                "value": 65
            },
            {
                "key": 300,
                "value": 113
            },
            {
                "key": 310,
                "value": 115
            },
            {
                "key": 320,
                "value": 152
            },
            {
                "key": 330,
                "value": 168
            },
            {
                "key": 340,
                "value": 231
            },
            {
                "key": 350,
                "value": 242
            },
            {
                "key": 360,
                "value": 278
            },
            {
                "key": 370,
                "value": 292
            },
            {
                "key": 380,
                "value": 287
            },
            {
                "key": 390,
                "value": 299
            },
            {
                "key": 400,
                "value": 347
            },
            {
                "key": 410,
                "value": 364
            },
            {
                "key": 420,
                "value": 334
            },
            {
                "key": 430,
                "value": 367
            },
            {
                "key": 440,
                "value": 327
            },
            {
                "key": 450,
                "value": 302
            },
            {
                "key": 460,
                "value": 318
            },
            {
                "key": 470,
                "value": 309
            },
            {
                "key": 480,
                "value": 334
            },
            {
                "key": 490,
                "value": 300
            },
            {
                "key": 500,
                "value": 267
            },
            {
                "key": 510,
                "value": 249
            },
            {
                "key": 520,
                "value": 244
            },
            {
                "key": 530,
                "value": 222
            },
            {
                "key": 540,
                "value": 218
            },
            {
                "key": 550,
                "value": 188
            },
            {
                "key": 560,
                "value": 187
            },
            {
                "key": 570,
                "value": 167
            },
            {
                "key": 580,
                "value": 150
            },
            {
                "key": 590,
                "value": 134
            },
            {
                "key": 600,
                "value": 134
            },
            {
                "key": 610,
                "value": 128
            },
            {
                "key": 620,
                "value": 113
            },
            {
                "key": 630,
                "value": 106
            },
            {
                "key": 640,
                "value": 100
            },
            {
                "key": 650,
                "value": 102
            },
            {
                "key": 660,
                "value": 80
            },
            {
                "key": 670,
                "value": 84
            },
            {
                "key": 680,
                "value": 88
            },
            {
                "key": 690,
                "value": 74
            },
            {
                "key": 700,
                "value": 59
            },
            {
                "key": 710,
                "value": 69
            },
            {
                "key": 720,
                "value": 44
            },
            {
                "key": 730,
                "value": 58
            },
            {
                "key": 740,
                "value": 42
            },
            {
                "key": 750,
                "value": 30
            },
            {
                "key": 760,
                "value": 36
            },
            {
                "key": 770,
                "value": 31
            },
            {
                "key": 780,
                "value": 21
            },
            {
                "key": 790,
                "value": 27
            },
            {
                "key": 800,
                "value": 18
            },
            {
                "key": 810,
                "value": 17
            },
            {
                "key": 820,
                "value": 23
            },
            {
                "key": 830,
                "value": 12
            },
            {
                "key": 840,
                "value": 12
            },
            {
                "key": 850,
                "value": 15
            },
            {
                "key": 860,
                "value": 12
            },
            {
                "key": 870,
                "value": 15
            },
            {
                "key": 880,
                "value": 15
            },
            {
                "key": 890,
                "value": 9
            },
            {
                "key": 900,
                "value": 10
            },
            {
                "key": 910,
                "value": 18
            },
            {
                "key": 920,
                "value": 16
            },
            {
                "key": 930,
                "value": 24
            },
            {
                "key": 940,
                "value": 20
            },
            {
                "key": 950,
                "value": 41
            },
            {
                "key": 960,
                "value": 39
            },
            {
                "key": 970,
                "value": 26
            },
            {
                "key": 980,
                "value": 24
            },
            {
                "key": 990,
                "value": 43
            },
            {
                "key": 1000,
                "value": 42
            },
            {
                "key": 1010,
                "value": 32
            },
            {
                "key": 1020,
                "value": 34
            },
            {
                "key": 1030,
                "value": 35
            },
            {
                "key": 1040,
                "value": 25
            },
            {
                "key": 1050,
                "value": 37
            },
            {
                "key": 1060,
                "value": 26
            },
            {
                "key": 1070,
                "value": 19
            },
            {
                "key": 1080,
                "value": 22
            },
            {
                "key": 1090,
                "value": 24
            },
            {
                "key": 1100,
                "value": 14
            },
            {
                "key": 1110,
                "value": 20
            },
            {
                "key": 1120,
                "value": 15
            },
            {
                "key": 1130,
                "value": 13
            },
            {
                "key": 1140,
                "value": 9
            },
            {
                "key": 1150,
                "value": 10
            },
            {
                "key": 1160,
                "value": 5
            },
            {
                "key": 1170,
                "value": 8
            },
            {
                "key": 1180,
                "value": 3
            },
            {
                "key": 1190,
                "value": 3
            },
            {
                "key": 1200,
                "value": 5
            },
            {
                "key": 1210,
                "value": 2
            },
            {
                "key": 1220,
                "value": 7
            },
            {
                "key": 1230,
                "value": 2
            },
            {
                "key": 1240,
                "value": 2
            },
            {
                "key": 1250,
                "value": 4
            },
            {
                "key": 1260,
                "value": 2
            },
            {
                "key": 1290,
                "value": 1
            },
            {
                "key": 1310,
                "value": 1
            },
            {
                "key": 1320,
                "value": 1
            },
            {
                "key": 1350,
                "value": 2
            },
            {
                "key": 1380,
                "value": 1
            }
        ],
        "bestBracket": "101001111100101101001011110101111101110000001110111011000101111"
    }
}