{
    "VERSION": "1.2",
    "format": "TTT",
    "statistics": {
        "max": 1590,
        "frequencyTable": [
            {
                "key": 170,
                "value": 1
            },
            {
                "key": 180,
                "value": 1
            },
            {
                "key": 190,
                "value": 6
            },
            {
                "key": 200,
                "value": 10
            },
            {
                "key": 210,
                "value": 15
            },
            {
                "key": 220,
                "value": 37
            },
            {
                "key": 230,
                "value": 67
            },
            {
                "key": 240,
                "value": 129
            },
            {
                "key": 250,
                "value": 195
            },
            {
                "key": 260,
                "value": 263
            },
            {
                "key": 270,
                "value": 378
            },
            {
                "key": 280,
                "value": 569
            },
            {
                "key": 290,
                "value": 740
            },
            {
                "key": 300,
                "value": 1014
            },
            {
                "key": 310,
                "value": 1301
            },
            {
                "key": 320,
                "value": 1605
            },
            {
                "key": 330,
                "value": 1834
            },
            {
                "key": 340,
                "value": 2162
            },
            {
                "key": 350,
                "value": 2521
            },
            {
                "key": 360,
                "value": 2728
            },
            {
                "key": 370,
                "value": 2996
            },
            {
                "key": 380,
                "value": 3260
            },
            {
                "key": 390,
                "value": 3386
            },
            {
                "key": 400,
                "value": 3298
            },
            {
                "key": 410,
                "value": 3518
            },
            {
                "key": 420,
                "value": 3604
            },
            {
                "key": 430,
                "value": 3538
            },
            {
                "key": 440,
                "value": 3510
            },
            {
                "key": 450,
                "value": 3515
            },
            {
                "key": 460,
                "value": 3269
            },
            {
                "key": 470,
                "value": 3204
            },
            {
                "key": 480,
                "value": 3153
            },
            {
                "key": 490,
                "value": 2995
            },
            {
                "key": 500,
                "value": 2821
            },
            {
                "key": 510,
                "value": 2600
            },
            {
                "key": 520,
                "value": 2485
            },
            {
                "key": 530,
                "value": 2316
            },
            {
                "key": 540,
                "value": 2086
            },
            {
                "key": 550,
                "value": 1863
            },
            {
                "key": 560,
                "value": 1619
            },
            {
                "key": 570,
                "value": 1481
            },
            {
                "key": 580,
                "value": 1374
            },
            {
                "key": 590,
                "value": 1265
            },
            {
                "key": 600,
                "value": 1176
            },
            {
                "key": 610,
                "value": 1095
            },
            {
                "key": 620,
                "value": 1013
            },
            {
                "key": 630,
                "value": 929
            },
            {
                "key": 640,
                "value": 898
            },
            {
                "key": 650,
                "value": 887
            },
            {
                "key": 660,
                "value": 813
            },
            {
                "key": 670,
                "value": 757
            },
            {
                "key": 680,
                "value": 727
            },
            {
                "key": 690,
                "value": 695
            },
            {
                "key": 700,
                "value": 635
            },
            {
                "key": 710,
                "value": 543
            },
            {
                "key": 720,
                "value": 498
            },
            {
                "key": 730,
                "value": 463
            },
            {
                "key": 740,
                "value": 398
            },
            {
                "key": 750,
                "value": 360
            },
            {
                "key": 760,
                "value": 284
            },
            {
                "key": 770,
                "value": 263
            },
            {
                "key": 780,
                "value": 216
            },
            {
                "key": 790,
                "value": 177
            },
            {
                "key": 800,
                "value": 169
            },
            {
                "key": 810,
                "value": 131
            },
            {
                "key": 820,
                "value": 97
            },
            {
                "key": 830,
                "value": 95
            },
            {
                "key": 840,
                "value": 101
            },
            {
                "key": 850,
                "value": 93
            },
            {
                "key": 860,
                "value": 76
            },
            {
                "key": 870,
                "value": 120
            },
            {
                "key": 880,
                "value": 114
            },
            {
                "key": 890,
                "value": 143
            },
            {
                "key": 900,
                "value": 184
            },
            {
                "key": 910,
                "value": 208
            },
            {
                "key": 920,
                "value": 258
            },
            {
                "key": 930,
                "value": 284
            },
            {
                "key": 940,
                "value": 332
            },
            {
                "key": 950,
                "value": 383
            },
            {
                "key": 960,
                "value": 401
            },
            {
                "key": 970,
                "value": 406
            },
            {
                "key": 980,
                "value": 427
            },
            {
                "key": 990,
                "value": 425
            },
            {
                "key": 1000,
                "value": 402
            },
            {
                "key": 1010,
                "value": 443
            },
            {
                "key": 1020,
                "value": 412
            },
            {
                "key": 1030,
                "value": 387
            },
            {
                "key": 1040,
                "value": 317
            },
            {
                "key": 1050,
                "value": 323
            },
            {
                "key": 1060,
                "value": 266
            },
            {
                "key": 1070,
                "value": 237
            },
            {
                "key": 1080,
                "value": 189
            },
            {
                "key": 1090,
                "value": 146
            },
            {
                "key": 1100,
                "value": 149
            },
            {
                "key": 1110,
                "value": 121
            },
            {
                "key": 1120,
                "value": 109
            },
            {
                "key": 1130,
                "value": 80
            },
            {
                "key": 1140,
                "value": 82
            },
            {
                "key": 1150,
                "value": 60
            },
            {
                "key": 1160,
                "value": 35
            },
            {
                "key": 1170,
                "value": 46
            },
            {
                "key": 1180,
                "value": 25
            },
            {
                "key": 1190,
                "value": 23
            },
            {
                "key": 1200,
                "value": 18
            },
            {
                "key": 1210,
                "value": 14
            },
            {
                "key": 1220,
                "value": 15
            },
            {
                "key": 1230,
                "value": 11
            },
            {
                "key": 1240,
                "value": 6
            },
            {
                "key": 1250,
                "value": 7
            },
            {
                "key": 1260,
                "value": 15
            },
            {
                "key": 1270,
                "value": 8
            },
            {
                "key": 1280,
                "value": 9
            },
            {
                "key": 1290,
                "value": 2
            },
            {
                "key": 1300,
                "value": 8
            },
            {
                "key": 1310,
                "value": 3
            },
            {
                "key": 1320,
                "value": 5
            },
            {
                "key": 1340,
                "value": 5
            },
            {
                "key": 1350,
                "value": 4
            },
            {
                "key": 1360,
                "value": 1
            },
            {
                "key": 1370,
                "value": 1
            },
            {
                "key": 1380,
                "value": 2
            },
            {
                "key": 1390,
                "value": 3
            },
            {
                "key": 1400,
                "value": 1
            },
            {
                "key": 1410,
                "value": 2
            },
            {
                "key": 1430,
                "value": 1
            },
            {
                "key": 1590,
                "value": 1
            }
        ],
        "bestBracket": "101111101100101101111010000101100101011001011111110111010001111"
    }
}