{
    "VERSION": "1.2",
    "format": "TTT",
    "statistics": {
        "max": 1530,
        "frequencyTable": [
            {
                "key": 230,
                "value": 1
            },
            {
                "key": 250,
                "value": 3
            },
            {
                "key": 260,
                "value": 1
            },
            {
                "key": 270,
                "value": 3
            },
            {
                "key": 280,
                "value": 7
            },
            {
                "key": 290,
                "value": 10
            },
            {
                "key": 300,
                "value": 14
            },
            {
                "key": 310,
                "value": 13
            },
            {
                "key": 320,
                "value": 8
            },
            {
                "key": 330,
                "value": 28
            },
            {
                "key": 340,
                "value": 44
            },
            {
                "key": 350,
                "value": 40
            },
            {
                "key": 360,
                "value": 57
            },
            {
                "key": 370,
                "value": 68
            },
            {
                "key": 380,
                "value": 84
            },
            {
                "key": 390,
                "value": 102
            },
            {
                "key": 400,
                "value": 109
            },
            {
                "key": 410,
                "value": 144
            },
            {
                "key": 420,
                "value": 151
            },
            {
                "key": 430,
                "value": 171
            },
            {
                "key": 440,
                "value": 206
            },
            {
                "key": 450,
                "value": 239
            },
            {
                "key": 460,
                "value": 248
            },
            {
                "key": 470,
                "value": 260
            },
            {
                "key": 480,
                "value": 269
            },
            {
                "key": 490,
                "value": 262
            },
            {
                "key": 500,
                "value": 268
            },
            {
                "key": 510,
                "value": 300
            },
            {
                "key": 520,
                "value": 297
            },
            {
                "key": 530,
                "value": 320
            },
            {
                "key": 540,
                "value": 301
            },
            {
                "key": 550,
                "value": 307
            },
            {
                "key": 560,
                "value": 306
            },
            {
                "key": 570,
                "value": 357
            },
            {
                "key": 580,
                "value": 310
            },
            {
                "key": 590,
                "value": 257
            },
            {
                "key": 600,
                "value": 292
            },
            {
                "key": 610,
                "value": 283
            },
            {
                "key": 620,
                "value": 267
            },
            {
                "key": 630,
                "value": 223
            },
            {
                "key": 640,
                "value": 218
            },
            {
                "key": 650,
                "value": 225
            },
            {
                "key": 660,
                "value": 207
            },
            {
                "key": 670,
                "value": 183
            },
            {
                "key": 680,
                "value": 166
            },
            {
                "key": 690,
                "value": 192
            },
            {
                "key": 700,
                "value": 176
            },
            {
                "key": 710,
                "value": 157
            },
            {
                "key": 720,
                "value": 134
            },
            {
                "key": 730,
                "value": 139
            },
            {
                "key": 740,
                "value": 108
            },
            {
                "key": 750,
                "value": 126
            },
            {
                "key": 760,
                "value": 105
            },
            {
                "key": 770,
                "value": 110
            },
            {
                "key": 780,
                "value": 95
            },
            {
                "key": 790,
                "value": 90
            },
            {
                "key": 800,
                "value": 75
            },
            {
                "key": 810,
                "value": 74
            },
            {
                "key": 820,
                "value": 71
            },
            {
                "key": 830,
                "value": 63
            },
            {
                "key": 840,
                "value": 49
            },
            {
                "key": 850,
                "value": 46
            },
            {
                "key": 860,
                "value": 42
            },
            {
                "key": 870,
                "value": 42
            },
            {
                "key": 880,
                "value": 50
            },
            {
                "key": 890,
                "value": 33
            },
            {
                "key": 900,
                "value": 37
            },
            {
                "key": 910,
                "value": 23
            },
            {
                "key": 920,
                "value": 22
            },
            {
                "key": 930,
                "value": 21
            },
            {
                "key": 940,
                "value": 20
            },
            {
                "key": 950,
                "value": 22
            },
            {
                "key": 960,
                "value": 9
            },
            {
                "key": 970,
                "value": 13
            },
            {
                "key": 980,
                "value": 11
            },
            {
                "key": 990,
                "value": 18
            },
            {
                "key": 1000,
                "value": 7
            },
            {
                "key": 1010,
                "value": 11
            },
            {
                "key": 1020,
                "value": 7
            },
            {
                "key": 1030,
                "value": 7
            },
            {
                "key": 1040,
                "value": 6
            },
            {
                "key": 1050,
                "value": 6
            },
            {
                "key": 1060,
                "value": 8
            },
            {
                "key": 1070,
                "value": 4
            },
            {
                "key": 1080,
                "value": 6
            },
            {
                "key": 1090,
                "value": 11
            },
            {
                "key": 1100,
                "value": 6
            },
            {
                "key": 1110,
                "value": 7
            },
            {
                "key": 1120,
                "value": 4
            },
            {
                "key": 1130,
                "value": 11
            },
            {
                "key": 1140,
                "value": 7
            },
            {
                "key": 1150,
                "value": 5
            },
            {
                "key": 1160,
                "value": 3
            },
            {
                "key": 1170,
                "value": 6
            },
            {
                "key": 1180,
                "value": 4
            },
            {
                "key": 1190,
                "value": 6
            },
            {
                "key": 1200,
                "value": 7
            },
            {
                "key": 1210,
                "value": 7
            },
            {
                "key": 1220,
                "value": 7
            },
            {
                "key": 1230,
                "value": 2
            },
            {
                "key": 1240,
                "value": 5
            },
            {
                "key": 1250,
                "value": 1
            },
            {
                "key": 1260,
                "value": 2
            },
            {
                "key": 1270,
                "value": 3
            },
            {
                "key": 1280,
                "value": 4
            },
            {
                "key": 1300,
                "value": 2
            },
            {
                "key": 1310,
                "value": 3
            },
            {
                "key": 1320,
                "value": 1
            },
            {
                "key": 1330,
                "value": 2
            },
            {
                "key": 1340,
                "value": 1
            },
            {
                "key": 1350,
                "value": 3
            },
            {
                "key": 1360,
                "value": 2
            },
            {
                "key": 1370,
                "value": 2
            },
            {
                "key": 1380,
                "value": 1
            },
            {
                "key": 1410,
                "value": 2
            },
            {
                "key": 1440,
                "value": 2
            },
            {
                "key": 1450,
                "value": 1
            },
            {
                "key": 1470,
                "value": 2
            },
            {
                "key": 1480,
                "value": 2
            },
            {
                "key": 1490,
                "value": 1
            },
            {
                "key": 1530,
                "value": 1
            }
        ],
        "bestBracket": "110101111010000111111011111111101111111111111110111011111100111"
    }
}