{
    "VERSION": "1.2",
    "format": "TTT",
    "statistics": {
        "max": 1500,
        "frequencyTable": [
            {
                "key": 250,
                "value": 3
            },
            {
                "key": 260,
                "value": 1
            },
            {
                "key": 270,
                "value": 1
            },
            {
                "key": 280,
                "value": 3
            },
            {
                "key": 290,
                "value": 6
            },
            {
                "key": 300,
                "value": 9
            },
            {
                "key": 310,
                "value": 14
            },
            {
                "key": 320,
                "value": 12
            },
            {
                "key": 330,
                "value": 21
            },
            {
                "key": 340,
                "value": 33
            },
            {
                "key": 350,
                "value": 46
            },
            {
                "key": 360,
                "value": 59
            },
            {
                "key": 370,
                "value": 52
            },
            {
                "key": 380,
                "value": 88
            },
            {
                "key": 390,
                "value": 110
            },
            {
                "key": 400,
                "value": 95
            },
            {
                "key": 410,
                "value": 124
            },
            {
                "key": 420,
                "value": 138
            },
            {
                "key": 430,
                "value": 180
            },
            {
                "key": 440,
                "value": 196
            },
            {
                "key": 450,
                "value": 194
            },
            {
                "key": 460,
                "value": 237
            },
            {
                "key": 470,
                "value": 241
            },
            {
                "key": 480,
                "value": 266
            },
            {
                "key": 490,
                "value": 258
            },
            {
                "key": 500,
                "value": 288
            },
            {
                "key": 510,
                "value": 304
            },
            {
                "key": 520,
                "value": 302
            },
            {
                "key": 530,
                "value": 317
            },
            {
                "key": 540,
                "value": 304
            },
            {
                "key": 550,
                "value": 325
            },
            {
                "key": 560,
                "value": 295
            },
            {
                "key": 570,
                "value": 268
            },
            {
                "key": 580,
                "value": 312
            },
            {
                "key": 590,
                "value": 297
            },
            {
                "key": 600,
                "value": 279
            },
            {
                "key": 610,
                "value": 254
            },
            {
                "key": 620,
                "value": 270
            },
            {
                "key": 630,
                "value": 251
            },
            {
                "key": 640,
                "value": 234
            },
            {
                "key": 650,
                "value": 182
            },
            {
                "key": 660,
                "value": 234
            },
            {
                "key": 670,
                "value": 195
            },
            {
                "key": 680,
                "value": 180
            },
            {
                "key": 690,
                "value": 191
            },
            {
                "key": 700,
                "value": 172
            },
            {
                "key": 710,
                "value": 166
            },
            {
                "key": 720,
                "value": 156
            },
            {
                "key": 730,
                "value": 170
            },
            {
                "key": 740,
                "value": 128
            },
            {
                "key": 750,
                "value": 136
            },
            {
                "key": 760,
                "value": 112
            },
            {
                "key": 770,
                "value": 99
            },
            {
                "key": 780,
                "value": 103
            },
            {
                "key": 790,
                "value": 108
            },
            {
                "key": 800,
                "value": 91
            },
            {
                "key": 810,
                "value": 86
            },
            {
                "key": 820,
                "value": 78
            },
            {
                "key": 830,
                "value": 65
            },
            {
                "key": 840,
                "value": 62
            },
            {
                "key": 850,
                "value": 44
            },
            {
                "key": 860,
                "value": 48
            },
            {
                "key": 870,
                "value": 47
            },
            {
                "key": 880,
                "value": 42
            },
            {
                "key": 890,
                "value": 32
            },
            {
                "key": 900,
                "value": 26
            },
            {
                "key": 910,
                "value": 28
            },
            {
                "key": 920,
                "value": 39
            },
            {
                "key": 930,
                "value": 23
            },
            {
                "key": 940,
                "value": 19
            },
            {
                "key": 950,
                "value": 18
            },
            {
                "key": 960,
                "value": 15
            },
            {
                "key": 970,
                "value": 16
            },
            {
                "key": 980,
                "value": 6
            },
            {
                "key": 990,
                "value": 7
            },
            {
                "key": 1000,
                "value": 8
            },
            {
                "key": 1010,
                "value": 7
            },
            {
                "key": 1020,
                "value": 2
            },
            {
                "key": 1030,
                "value": 10
            },
            {
                "key": 1040,
                "value": 6
            },
            {
                "key": 1050,
                "value": 8
            },
            {
                "key": 1060,
                "value": 9
            },
            {
                "key": 1070,
                "value": 4
            },
            {
                "key": 1080,
                "value": 7
            },
            {
                "key": 1090,
                "value": 8
            },
            {
                "key": 1100,
                "value": 6
            },
            {
                "key": 1110,
                "value": 8
            },
            {
                "key": 1120,
                "value": 3
            },
            {
                "key": 1130,
                "value": 2
            },
            {
                "key": 1140,
                "value": 6
            },
            {
                "key": 1150,
                "value": 4
            },
            {
                "key": 1160,
                "value": 3
            },
            {
                "key": 1170,
                "value": 9
            },
            {
                "key": 1180,
                "value": 5
            },
            {
                "key": 1190,
                "value": 7
            },
            {
                "key": 1200,
                "value": 7
            },
            {
                "key": 1210,
                "value": 5
            },
            {
                "key": 1220,
                "value": 3
            },
            {
                "key": 1230,
                "value": 7
            },
            {
                "key": 1240,
                "value": 2
            },
            {
                "key": 1250,
                "value": 3
            },
            {
                "key": 1260,
                "value": 1
            },
            {
                "key": 1270,
                "value": 3
            },
            {
                "key": 1280,
                "value": 2
            },
            {
                "key": 1300,
                "value": 1
            },
            {
                "key": 1310,
                "value": 3
            },
            {
                "key": 1320,
                "value": 5
            },
            {
                "key": 1340,
                "value": 2
            },
            {
                "key": 1350,
                "value": 3
            },
            {
                "key": 1370,
                "value": 2
            },
            {
                "key": 1380,
                "value": 3
            },
            {
                "key": 1400,
                "value": 2
            },
            {
                "key": 1410,
                "value": 1
            },
            {
                "key": 1420,
                "value": 2
            },
            {
                "key": 1440,
                "value": 2
            },
            {
                "key": 1460,
                "value": 2
            },
            {
                "key": 1470,
                "value": 1
            },
            {
                "key": 1480,
                "value": 3
            },
            {
                "key": 1500,
                "value": 2
            }
        ],
        "bestBracket": "100100111100100100101111000000110111111110111110111111110100111"
    }
}